[
  {
    "level": "level_1",
    "backend": "trocr-riksarkivet",
    "pooling": "mean",
    "metrics": {
      "fd": 0.3100937630627989,
      "ed": 0.45551202574500477,
      "fd_inf": 0.2927689401898624,
      "ed_inf": 0.4515110119173557
    }
  },
  {
    "level": "level_1",
    "backend": "trocr-riksarkivet",
    "pooling": "max",
    "metrics": {
      "fd": 2.46734108460862,
      "ed": 0.734341093196648,
      "fd_inf": 1.1271566718148396,
      "ed_inf": 0.7269831988655026
    }
  },
  {
    "level": "level_1",
    "backend": "trocr-riksarkivet",
    "pooling": "cls",
    "metrics": {
      "fd": 0.01636625603780506,
      "ed": 0.10612103426987467,
      "fd_inf": 0.015364325606529968,
      "ed_inf": 0.1047858927573743
    }
  },
  {
    "level": "level_2",
    "backend": "trocr-riksarkivet",
    "pooling": "mean",
    "metrics": {
      "fd": 0.6222956021061137,
      "ed": 0.6402122263215976,
      "fd_inf": 0.5854482987529447,
      "ed_inf": 0.6353307200599525
    }
  },
  {
    "level": "level_2",
    "backend": "trocr-riksarkivet",
    "pooling": "max",
    "metrics": {
      "fd": 4.4645565209684435,
      "ed": 1.0307205653187552,
      "fd_inf": 2.2883613953022808,
      "ed_inf": 1.0239083990383613
    }
  },
  {
    "level": "level_2",
    "backend": "trocr-riksarkivet",
    "pooling": "cls",
    "metrics": {
      "fd": 0.03524017636535581,
      "ed": 0.15283349582586753,
      "fd_inf": 0.033064763778008974,
      "ed_inf": 0.15122734680002622
    }
  },
  {
    "level": "level_3",
    "backend": "trocr-riksarkivet",
    "pooling": "mean",
    "metrics": {
      "fd": 1.049420411821373,
      "ed": 0.826912684332564,
      "fd_inf": 1.0061288791344445,
      "ed_inf": 0.8229677788393367
    }
  },
  {
    "level": "level_3",
    "backend": "trocr-riksarkivet",
    "pooling": "max",
    "metrics": {
      "fd": 6.404091385324534,
      "ed": 1.3613178967036053,
      "fd_inf": 3.9973239402071394,
      "ed_inf": 1.3551799300371805
    }
  },
  {
    "level": "level_3",
    "backend": "trocr-riksarkivet",
    "pooling": "cls",
    "metrics": {
      "fd": 0.05969227654373466,
      "ed": 0.1993566374124487,
      "fd_inf": 0.05713674862184125,
      "ed_inf": 0.19796991538722675
    }
  },
  {
    "level": "level_4",
    "backend": "trocr-riksarkivet",
    "pooling": "mean",
    "metrics": {
      "fd": 1.4816555558310007,
      "ed": 0.9910513196494578,
      "fd_inf": 1.4327698241088036,
      "ed_inf": 0.9882493480745623
    }
  },
  {
    "level": "level_4",
    "backend": "trocr-riksarkivet",
    "pooling": "max",
    "metrics": {
      "fd": 8.225494762059554,
      "ed": 1.6164863024591258,
      "fd_inf": 5.558566555331968,
      "ed_inf": 1.6096833706450986
    }
  },
  {
    "level": "level_4",
    "backend": "trocr-riksarkivet",
    "pooling": "cls",
    "metrics": {
      "fd": 0.0849543683021372,
      "ed": 0.23812057258578379,
      "fd_inf": 0.08194754346838366,
      "ed_inf": 0.23704531655332742
    }
  },
  {
    "level": "level_5",
    "backend": "trocr-riksarkivet",
    "pooling": "mean",
    "metrics": {
      "fd": 2.8290693632042014,
      "ed": 1.3832933161638392,
      "fd_inf": 2.7734601403864283,
      "ed_inf": 1.3828553582431646
    }
  },
  {
    "level": "level_5",
    "backend": "trocr-riksarkivet",
    "pooling": "max",
    "metrics": {
      "fd": 13.713207747314016,
      "ed": 2.2691120058533962,
      "fd_inf": 10.710130834393766,
      "ed_inf": 2.2659990226166675
    }
  },
  {
    "level": "level_5",
    "backend": "trocr-riksarkivet",
    "pooling": "cls",
    "metrics": {
      "fd": 0.15244953703189013,
      "ed": 0.32211348017639335,
      "fd_inf": 0.14864651140915355,
      "ed_inf": 0.32113260910501795
    }
  },
  {
    "level": "level_6",
    "backend": "trocr-riksarkivet",
    "pooling": "mean",
    "metrics": {
      "fd": 4.190859357273212,
      "ed": 1.7000093886977714,
      "fd_inf": 4.118309427147933,
      "ed_inf": 1.6984659942803122
    }
  },
  {
    "level": "level_6",
    "backend": "trocr-riksarkivet",
    "pooling": "max",
    "metrics": {
      "fd": 19.14489870765817,
      "ed": 2.810904410933207,
      "fd_inf": 15.865962347131164,
      "ed_inf": 2.8028007639933272
    }
  },
  {
    "level": "level_6",
    "backend": "trocr-riksarkivet",
    "pooling": "cls",
    "metrics": {
      "fd": 0.23815057076779844,
      "ed": 0.4044308552709172,
      "fd_inf": 0.23350570293259168,
      "ed_inf": 0.40359538254261196
    }
  },
  {
    "level": "level_7",
    "backend": "trocr-riksarkivet",
    "pooling": "mean",
    "metrics": {
      "fd": 4.873243973771704,
      "ed": 1.8177682942206899,
      "fd_inf": 4.794816730098,
      "ed_inf": 1.8160364004378495
    }
  },
  {
    "level": "level_7",
    "backend": "trocr-riksarkivet",
    "pooling": "max",
    "metrics": {
      "fd": 22.18935661824176,
      "ed": 3.067093755916574,
      "fd_inf": 18.842667455539537,
      "ed_inf": 3.060613866400644
    }
  },
  {
    "level": "level_7",
    "backend": "trocr-riksarkivet",
    "pooling": "cls",
    "metrics": {
      "fd": 0.2806417947993354,
      "ed": 0.43766284263898875,
      "fd_inf": 0.27552071821234037,
      "ed_inf": 0.4367195601414792
    }
  },
  {
    "level": "level_8",
    "backend": "trocr-riksarkivet",
    "pooling": "mean",
    "metrics": {
      "fd": 6.411731975802031,
      "ed": 2.1228426814287573,
      "fd_inf": 6.329191209609786,
      "ed_inf": 2.1211823996642134
    }
  },
  {
    "level": "level_8",
    "backend": "trocr-riksarkivet",
    "pooling": "max",
    "metrics": {
      "fd": 27.2526574573547,
      "ed": 3.513415312879519,
      "fd_inf": 23.84455314423296,
      "ed_inf": 3.5079938029989637
    }
  },
  {
    "level": "level_8",
    "backend": "trocr-riksarkivet",
    "pooling": "cls",
    "metrics": {
      "fd": 0.362248238063825,
      "ed": 0.5017847140844227,
      "fd_inf": 0.3563703546280457,
      "ed_inf": 0.5006061958696087
    }
  },
  {
    "level": "level_9",
    "backend": "trocr-riksarkivet",
    "pooling": "mean",
    "metrics": {
      "fd": 7.8289530758260355,
      "ed": 2.340715753514557,
      "fd_inf": 7.745049651234326,
      "ed_inf": 2.338779032911199
    }
  },
  {
    "level": "level_9",
    "backend": "trocr-riksarkivet",
    "pooling": "max",
    "metrics": {
      "fd": 32.764042849655794,
      "ed": 3.9024219587795543,
      "fd_inf": 29.303079887482003,
      "ed_inf": 3.8958814540755617
    }
  },
  {
    "level": "level_9",
    "backend": "trocr-riksarkivet",
    "pooling": "cls",
    "metrics": {
      "fd": 0.4502193805189554,
      "ed": 0.5613135893419405,
      "fd_inf": 0.44434782209463647,
      "ed_inf": 0.560126515041207
    }
  },
  {
    "level": "level_10",
    "backend": "trocr-riksarkivet",
    "pooling": "mean",
    "metrics": {
      "fd": 10.999724311543051,
      "ed": 2.8165463456550244,
      "fd_inf": 10.890386172683789,
      "ed_inf": 2.8114103071557097
    }
  },
  {
    "level": "level_10",
    "backend": "trocr-riksarkivet",
    "pooling": "max",
    "metrics": {
      "fd": 44.600655650824024,
      "ed": 4.767948446745054,
      "fd_inf": 41.024589245260984,
      "ed_inf": 4.759569334064895
    }
  },
  {
    "level": "level_10",
    "backend": "trocr-riksarkivet",
    "pooling": "cls",
    "metrics": {
      "fd": 0.6248482735912075,
      "ed": 0.6672795493088434,
      "fd_inf": 0.6174823293721069,
      "ed_inf": 0.6653123211531277
    }
  }
]